primapy_optimus_price/__init__.py
primapy_optimus_price-0.1.0.dist-info/METADATA
primapy_optimus_price-0.1.0.dist-info/WHEEL
primapy_optimus_price-0.1.0.dist-info/RECORD
